{
    "alpha-2": "FI",
    "alpha-3": "FIN",
    "numeric": "246",
    "names": {
        "en": "Finland",
        "fr": "Finlande",
        "ur": "فن لینڈ",
        "rn": "Finilandi",
        "lv": "Somija",
        "hy": "Ֆինլանդիա",
        "sq": "Finlandë",
        "jv": "Finlan",
        "or": "ଫିନଲ୍ୟାଣ୍ଡ",
        "mg": "Finlandy",
        "no": "Finland",
        "zh_Hant": "芬蘭",
        "tr": "Finlandiya",
        "bs_Cyrl": "Финска",
        "ja": "フィンランド",
        "th": "ฟินแลนด์",
        "bs": "Finska",
        "he": "פינלנד",
        "fa_AF": "فنلند",
        "kk": "Финляндия",
        "mo": "Finlanda",
        "ff": "Fenland",
        "ca": "Finlàndia",
        "ar": "فنلندا",
        "eu": "Finlandia",
        "ps": "فنلینډ",
        "kn": "ಫಿನ್‌ಲ್ಯಾಂಡ್",
        "si": "ෆින්ලන්තය",
        "km": "ហ្វាំងឡង់",
        "ne": "फिनल्याण्ड",
        "fi": "Suomi",
        "hi": "फ़िनलैंड",
        "rm": "Finlanda",
        "vi": "Phần Lan",
        "gl": "Finlandia",
        "ig": "Finland",
        "mr": "फिनलंड",
        "es": "Finlandia",
        "be": "Фінляндыя",
        "lg": "Finilandi",
        "az": "Finlandiya",
        "ce": "Финлянди",
        "mk": "Финска",
        "zu": "i-Finland",
        "it": "Finlandia",
        "ko": "핀란드",
        "lo": "ຟິນແລນ",
        "lt": "Suomija",
        "dz": "ཕིན་ལེནཌ",
        "ln": "Filandɛ",
        "hr": "Finska",
        "ks": "فِنلینڑ",
        "sv": "Finland",
        "pl": "Finlandia",
        "nb": "Finland",
        "sh": "Finska",
        "lu": "Filande",
        "nl": "Finland",
        "ky": "Финляндия",
        "bn": "ফিনল্যান্ড",
        "sd": "فن لينڊ",
        "fa": "فنلاند",
        "gd": "An Fhionnlann",
        "cs": "Finsko",
        "tk": "Finlýandiýa",
        "eo": "Finnlando",
        "mt": "il-Finlandja",
        "sr": "Финска",
        "wo": "Finlànd",
        "el": "Φινλανδία",
        "sn": "Finland",
        "pt": "Finlândia",
        "yi": "פֿינלאַנד",
        "is": "Finnland",
        "ta": "பின்லாந்து",
        "br": "Finland",
        "hu": "Finnország",
        "et": "Soome",
        "ku": "Fînlenda",
        "sk": "Fínsko",
        "sw": "Ufini",
        "zh": "芬兰",
        "te": "ఫిన్లాండ్",
        "ro": "Finlanda",
        "ki": "Ufini",
        "ak": "Finland",
        "tg": "Финляндия",
        "ml": "ഫിൻലാൻഡ്",
        "yo": "Orílẹ́ède Filandi",
        "de": "Finnland",
        "as": "ফিনলেণ্ড",
        "am": "ፊንላንድ",
        "se": "Suopma",
        "az_Cyrl": "Финландија",
        "ia": "Finlandia",
        "ti": "ፊንላንድ",
        "ru": "Финляндия",
        "ga": "an Fhionlainn",
        "bg": "Финландия",
        "my": "ဖင်လန်",
        "fy": "Finlân",
        "bm": "Finilandi",
        "gu": "ફિનલેન્ડ",
        "uz": "Finlandiya",
        "cy": "Y Ffindir",
        "ug": "فىنلاندىيە",
        "sr_Latn": "Finska",
        "nn": "Finland",
        "uk": "Фінляндія",
        "qu": "Finlandia",
        "tl": "Finland",
        "ms": "Finland",
        "yo_BJ": "Orílɛ́ède Filandi",
        "so": "Finland",
        "da": "Finland",
        "tt": "Финляндия",
        "af": "Finland",
        "ha": "Finlan",
        "iw": "פינלנד",
        "ee": "Finland nutome",
        "in": "Finlandia",
        "to": "Finilani",
        "sl": "Finska",
        "sg": "Fëlânde",
        "lb": "Finnland",
        "uz_Cyrl": "Финляндия",
        "fo": "Finnland",
        "mn": "Финлянд",
        "id": "Finlandia",
        "pa": "ਫਿਨਲੈਂਡ",
        "ka": "ფინეთი",
        "nd": "Finland",
        "kab": "Finland",
        "wa": "Finlande",
        "kw": "Pow Finn",
        "ht": "Fenlann",
        "nah": "Fintlālpan",
        "ba": "Финляндия",
        "ckb": "فینلاند",
        "sc": "Finlàndia",
        "ach": "Finlan",
        "zh_HK": "芬蘭",
        "ab": "Суоми",
        "pi": "फिन्लैंड",
        "jam": "Finlan",
        "nv": "Nahoditsʼǫʼłání Dineʼé Bikéyah",
        "bi": "Finland",
        "gez": "ፊንላንድ",
        "ay": "Phini suyu",
        "zh_TW": "芬蘭",
        "mi": "Hinerangi",
        "pap": "Finlandia",
        "oc": "Finlandia",
        "gv": "Finnlynn",
        "an": "Finlandia",
        "mhr": "Суоми",
        "cv": "Финлянди",
        "kl": "Finlandi",
        "crh": "Finlandiya",
        "ve": "Finland",
        "csb": "Fińskô",
        "zh_CN": "芬兰",
        "dv": "ފިންލޭންޑު",
        "haw": "Pinilana",
        "byn": "ፊንላንድ",
        "iu": "ᐃᓐᓚᓐᑦ",
        "tig": "ፊንላንድ",
        "wal": "ፊንላንድ",
        "ch": "Finlandia",
        "bn_IN": "ফিনল্যান্ড",
        "pt_BR": "Finlândia",
        "fur": "Finlande",
        "frp": "Finlande",
        "bar": "Finnland",
        "rw": "Finilande",
        "tt@iqtelif": "Finland (Suomi)",
        "fil": "Pinlandiya",
        "ace": "Finlandia",
        "xh": "Finland",
        "io": "Finlando",
        "na": "Pinrand",
        "chr": "ᏫᏂᎳᏂ",
        "gn": "Finland",
        "mai": "फिनल्यान्ड",
        "kv": "Суоми Му",
        "sr@latin": "Finska",
        "son": "Finlandi",
        "ast": "Finlandia",
        "nso": "Finland"
    },
    "3166-2": {
        "FI-01": {
            "code": "FI-01",
            "type": "Region",
            "names": {
                "en": "Ahvenanmaan lääni",
                "uk": "Аландські острови",
                "da": "Ahvenanmaan maakunta",
                "sc": "Ìsulas Åland",
                "be": "Аландскія астравы",
                "sr": "Авенанман макунта",
                "hu": "Åland",
                "zh_TW": "Ahvenanmaan maakunta",
                "lt": "Alandų salos",
                "nl": "Åland",
                "zh_CN": "奥兰府",
                "vi": "Ahvenanmaan lääni",
                "fr": "Åland",
                "sv": "Ålands län",
                "sl": "Åland",
                "de": "Åland",
                "pl": "Wyspy Alandzkie",
                "fi": "Ahvenanmaan lääni",
                "sr@latin": "Avenanman makunta",
                "it": "Isole Åland",
                "id": "Ahvenanmaan maakunta"
            }
        },
        "FI-02": {
            "code": "FI-02",
            "type": "Region",
            "names": {
                "en": "Etelä-Karjala",
                "uk": "Південна Карелія",
                "da": "Etelä-Karjala",
                "sc": "Carèlia meridionale",
                "be": "Паўднёвая Карэлія",
                "sr": "Етела-Карјала",
                "zh_TW": "Etel ä-Karjala",
                "nl": "Zuid-Karelië",
                "fr": "Carélie du Sud",
                "sv": "Södra Karelen",
                "de": "Südkarelien",
                "pl": "Karelia Południowa",
                "sr@latin": "Etela-Karjala",
                "it": "Carelia meridionale",
                "id": "Etelä-Karjala"
            }
        },
        "FI-03": {
            "code": "FI-03",
            "type": "Region",
            "names": {
                "en": "Etelä-Pohjanmaa",
                "uk": "Південна Остроботнія",
                "da": "Etelä-Pohjanmaa",
                "sc": "Ostrobòtnia meridionale",
                "be": "Паўднёвая Астработнія",
                "sr": "Етела-Појанма",
                "zh_TW": "Etel ä-Pohjanmaa",
                "nl": "Zuid-Österbotten",
                "fr": "Ostrobotnie du Sud",
                "sv": "Södra Österbotten",
                "de": "Südösterbotten",
                "pl": "Ostrobotnia Południowa",
                "sr@latin": "Etela-Pojanma",
                "it": "Ostrobotnia meridionale",
                "id": "Etelä-Pohjanmaa"
            }
        },
        "FI-04": {
            "code": "FI-04",
            "type": "Region",
            "names": {
                "en": "Haute-Savoie",
                "uk": "Південна Савонія",
                "da": "Etelä-Savo",
                "sc": "Savònia meridionale",
                "be": "Паўднёвае Сава",
                "sr": "Етела-Саво",
                "hu": "Haute-Savoie",
                "zh_TW": "Etel ä-Savo",
                "lt": "Aukštutinė Savoja",
                "nl": "Zuid-Savo",
                "oc": "Nauta Savòia",
                "zh_CN": "上萨瓦省",
                "vi": "Haute-Savoie",
                "fr": "Savonie du Sud",
                "sv": "Södra Savolax",
                "sl": "Haute-Savoie",
                "de": "Südsavo",
                "pl": "Sawonia Południowa",
                "sr@latin": "Etela-Savo",
                "it": "Savo meridionale",
                "id": "Etelä-Savo"
            }
        },
        "FI-05": {
            "code": "FI-05",
            "type": "Region",
            "names": {
                "en": "Kainuu",
                "uk": "Каїнуу",
                "da": "Kainuu",
                "sc": "Kainuu",
                "be": "Кайну",
                "zh_TW": "Kainuu",
                "nl": "Kainuu",
                "fr": "Kainuu",
                "sv": "Kajanaland",
                "de": "Kainuu",
                "pl": "Kainuu",
                "it": "Kainuu",
                "id": "Kainuu"
            }
        },
        "FI-06": {
            "code": "FI-06",
            "type": "Region",
            "names": {
                "en": "Santarem",
                "ca": "Saint Helena",
                "wa": "Canada",
                "uk": "Канта-Хяме",
                "eu": "Katar",
                "da": "Kanta-Häme",
                "sc": "Kanta-Häme",
                "ro": "Santarém",
                "be": "Канта-Хямэ",
                "hu": "Szent Mária",
                "zh_TW": "Kanta-Hä 我",
                "lt": "Santareno apygarda",
                "nl": "Kanta-Häme",
                "ve": "Qatar",
                "zh_CN": "圣塔伦",
                "cs": "Saint Helena",
                "eo": "Kataro",
                "tr": "Kanta-Hame",
                "vi": "Santarém",
                "fr": "Kanta-Häme",
                "sv": "Egentliga Tavastland",
                "ko": "몬타나",
                "ga": "San Héilin",
                "bs": "Saint Helena",
                "sl": "Santarém",
                "de": "Kanta-Häme",
                "lv": "San Mārīno",
                "es": "Qatar",
                "pl": "Kanta-Häme",
                "it": "Kanta-Häme",
                "az": "Müqəddəs Helena",
                "bg": "Света Елена",
                "id": "Kanta-Häme",
                "nso": "Qatar"
            }
        },
        "FI-07": {
            "code": "FI-07",
            "type": "Region",
            "names": {
                "en": "Keski-Pohjanmaa",
                "uk": "Центральна Остроботнія",
                "da": "Keski-Pohjanmaa",
                "sc": "Ostrobòtnia tzentrale",
                "be": "Цэнтральная Астработнія",
                "zh_TW": "Keski-Pohjanmaa",
                "nl": "Centraal-Österbotten",
                "fr": "Ostrobotnie-Centrale",
                "sv": "Keski-Pohjanmaa",
                "de": "Mittelösterbotten",
                "pl": "Ostrobotnia Środkowa",
                "it": "Ostrobotnia centrale",
                "id": "Keski-Pohjanmaa"
            }
        },
        "FI-08": {
            "code": "FI-08",
            "type": "Region",
            "names": {
                "en": "Keski-Suomi",
                "uk": "Центральна Фінляндія",
                "da": "Keski-Suomi",
                "sc": "Finlàndia tzentrale",
                "be": "Цэнтральная Фінляндыя",
                "zh_TW": "Keski-Suomi",
                "nl": "Centraal-Finland",
                "fr": "Finlande-Centrale",
                "sv": "Mellersta Finland",
                "de": "Mittelfinnland",
                "pl": "Finlandia Środkowa",
                "it": "Finlandia centrale",
                "id": "Keski-Suomi"
            }
        },
        "FI-09": {
            "code": "FI-09",
            "type": "Region",
            "names": {
                "en": "Kymenlaakso",
                "uk": "Кюменлааксо",
                "da": "Kymenlaakso",
                "sc": "Kymenlaakso",
                "be": "Кюменлаакса",
                "sr": "Кименлаксо",
                "zh_TW": "Kymenlaakso",
                "nl": "Kymenlaakso",
                "fr": "Vallée de la Kymi",
                "sv": "Kymmenedalen",
                "de": "Kymenlaakso",
                "pl": "Kymenlaakso",
                "sr@latin": "Kimenlakso",
                "it": "Kymenlaakso",
                "id": "Kymenlaakso"
            }
        },
        "FI-10": {
            "code": "FI-10",
            "type": "Region",
            "names": {
                "en": "Lappi",
                "uk": "Лаппі",
                "da": "Lappi",
                "sc": "Lapònia",
                "be": "Лапландыя",
                "sr": "Лапи",
                "zh_TW": "Lappi",
                "nl": "Lapland",
                "ja": "ラッピ",
                "fr": "Laponie",
                "sv": "Lappi",
                "de": "Lappland",
                "pl": "Laponia",
                "sr@latin": "Lapi",
                "it": "Lapponia",
                "id": "Lappi"
            }
        },
        "FI-11": {
            "code": "FI-11",
            "type": "Region",
            "names": {
                "en": "Granma",
                "ca": "Ghana",
                "wa": "Granma",
                "uk": "Пірканмаа",
                "eu": "Ghana",
                "da": "Pirkanmaa",
                "sc": "Pirkanmaa",
                "be": "Пірканма",
                "sr": "Пирканма",
                "hu": "Granma",
                "zh_TW": "Pirkanmaa",
                "lt": "Granma",
                "nl": "Pirkanmaa",
                "ve": "Ghana",
                "zh_CN": "格拉玛省",
                "cs": "Ghana",
                "eo": "Ganao",
                "tr": "Pirkanmaa",
                "vi": "Granma",
                "fr": "Pirkanmaa",
                "sv": "Birkaland",
                "ko": "가나",
                "ga": "Gána",
                "bs": "Gana",
                "sl": "Granma",
                "de": "Pirkanmaa",
                "lv": "Gana",
                "es": "Ghana",
                "pl": "Pirkanmaa",
                "sr@latin": "Pirkanma",
                "it": "Pirkanmaa",
                "az": "Qana",
                "bg": "Гана",
                "id": "Pirkanmaa",
                "nso": "Ghana"
            }
        },
        "FI-12": {
            "code": "FI-12",
            "type": "Region",
            "names": {
                "en": "Pohjanmaa",
                "uk": "Остроботнія",
                "da": "Pohjanmaa",
                "sc": "Ostrobòtnia",
                "be": "Астработнія",
                "sr": "Појанма",
                "zh_TW": "Pohjanmaa",
                "nl": "Österbotten",
                "fr": "Ostrobotnie",
                "sv": "Österbotten",
                "de": "Österbotten",
                "pl": "Ostrobotnia",
                "sr@latin": "Pojanma",
                "it": "Ostrobotnia",
                "id": "Pohjanmaa"
            }
        },
        "FI-13": {
            "code": "FI-13",
            "type": "Region",
            "names": {
                "en": "Pohjois-Karjala",
                "uk": "Північна Карелія",
                "da": "Pohjois-Karjala",
                "sc": "Carèlia setentrionale",
                "be": "Паўночная Карэлія",
                "zh_TW": "Pohjois-Karjala",
                "nl": "Noord-Karelië",
                "fr": "Carélie du Nord",
                "sv": "Norra Karelen",
                "de": "Nordkarelien",
                "pl": "Karelia Północna",
                "it": "Carelia settentrionale",
                "id": "Pohjois-Karjala"
            }
        },
        "FI-14": {
            "code": "FI-14",
            "type": "Region",
            "names": {
                "en": "Pohjois-Pohjanmaa",
                "uk": "Північна Остроботнія",
                "da": "Pohjois-Pohjanmaa",
                "sc": "Ostrobòtnia setentrionale",
                "be": "Паўночная Астработнія",
                "zh_TW": "Pohjois-Pohjanmaa",
                "nl": "Noord-Österbotten",
                "fr": "Ostrobotnie du Nord",
                "sv": "Norra Österbotten",
                "de": "Nordösterbotten",
                "pl": "Północna Ostrobotnia",
                "it": "Ostrobotnia settentrionale",
                "id": "Pohjois-Pohjanmaa"
            }
        },
        "FI-15": {
            "code": "FI-15",
            "type": "Region",
            "names": {
                "en": "Pohjois-Savo",
                "uk": "Північна Савонія",
                "da": "Pohjois-Savo",
                "sc": "Savònia setentrionale",
                "be": "Паўночнае Сава",
                "zh_TW": "Pohjois-Savo",
                "nl": "Noord-Savo",
                "fr": "Savonie du Nord",
                "sv": "Norra Savolax",
                "de": "Nordsavo",
                "pl": "Sawonia Północna",
                "it": "Savo settentrionale",
                "id": "Pohjois-Savo"
            }
        },
        "FI-16": {
            "code": "FI-16",
            "type": "Region",
            "names": {
                "en": "Päijät-Häme",
                "uk": "Пяйят-Хяме",
                "da": "Päijät-Häme",
                "sc": "Päijät-Häme",
                "be": "Пяят-Хямэ",
                "zh_TW": "Pä ij ät-Hä 我",
                "nl": "Päijät-Häme",
                "fr": "Päijät-Häme",
                "sv": "Päijänne-Tavastland",
                "de": "Päijät-Häme",
                "pl": "Päijät-Häme",
                "it": "Päijät-Häme",
                "id": "Päijät-Häme"
            }
        },
        "FI-17": {
            "code": "FI-17",
            "type": "Region",
            "names": {
                "en": "Satakunta",
                "uk": "Сатакунта",
                "da": "Satakunta",
                "sc": "Satakunta",
                "be": "Сатакунта",
                "sr": "Сатакунта",
                "zh_TW": "Satakunta",
                "nl": "Satakunta",
                "fr": "Satakunta",
                "sv": "Satakunta",
                "de": "Satakunta",
                "pl": "Satakunta",
                "sr@latin": "Satakunta",
                "it": "Satakunta",
                "id": "Satakunta"
            }
        },
        "FI-18": {
            "code": "FI-18",
            "type": "Region",
            "names": {
                "en": "Uusimaa",
                "uk": "Уусімаа",
                "da": "Uusimaa",
                "sc": "Uusimaa",
                "be": "Усіма",
                "sr": "Усима",
                "zh_TW": "Uusimaa",
                "nl": "Uusimaa",
                "fr": "Uusimaa",
                "sv": "Nyland",
                "de": "Uusimaa",
                "pl": "Uusimaa",
                "sr@latin": "Usima",
                "it": "Uusimaa",
                "id": "Uusimaa"
            }
        },
        "FI-19": {
            "code": "FI-19",
            "type": "Region",
            "names": {
                "en": "Varsinais-Suomi",
                "uk": "Питома Фінляндія",
                "da": "Varsinais-Suomi",
                "sc": "Finlàndia de su Sud-Ovest",
                "be": "Паўднёва-Заходняя Фінляндыя",
                "zh_TW": "Varsinais-Suomi",
                "nl": "Varsinais-Suomi",
                "fr": "Finlande du Sud-Ouest",
                "sv": "Egentliga Finland",
                "de": "Varsinais-Suomi",
                "pl": "Finlandia Właściwa",
                "it": "Varsinais-Suomi",
                "id": "Varsinais-Suomi"
            }
        }
    }
}